coreframe/__init__.py
coreframe/cache.py
coreframe/config.py
coreframe/corearray.py
coreframe/coredataset.py
coreframe/parallel.py
coreframe/_utils/__init__.py
coreframe/_utils/apply_by_area.py
coreframe/_utils/apply_by_time.py
coreframe-1.0.3.dist-info/LICENSE
coreframe-1.0.3.dist-info/METADATA
coreframe-1.0.3.dist-info/WHEEL
coreframe-1.0.3.dist-info/top_level.txt
coreframe-1.0.3.dist-info/RECORD
